src/FA.v
/* verilator lint_off WIDTH */
module FA #(
    parameter N = 32
)(
    input [N-1:0] A,
    input [N-1:0] B,
    input [N-1:0] Cin,
    output reg [N-1:0] S,
    output reg [N-1:0] Cout
    );
    
assign {Cout, S} = A + B + Cin;

endmodule

src/Compressor_42.sv
module Compressor_42(
    input [31:0] x [3:0],
    input [31:0] cin,
    output [31:0] cout,
    output [31:0] c,
    output [31:0] s
    );
    wire [31:0] sum_fa1;
    FA #(.N(32)) fa1 (.A(x[0]), .B(x[1]), .Cin(x[2]), .S(sum_fa1), .Cout(cout));
    FA #(.N(32)) fa2 (.A(x[3]), .B(sum_fa1), .Cin(cin), .S(s), .Cout(c));

endmodule

tb/Compressor_42_tb.sv
module Compressor_42_tb();

reg [31:0] x [3:0];
reg  [31:0] cin;
wire [31:0] cout;
wire [31:0] c;
wire [31:0] s;

integer i, j, idx;
reg [31:0] inputs;
Compressor_42 compressor_42 (.x(x), .cin(cin), .cout(cout), .c(c), .s(s));

initial begin 
    $dumpfile("Compressor_42.vcd");
    $dumpvars(0, Compressor_42_tb);
    for (idx = 0; idx < 4; idx = idx + 1) $dumpvars(0, x[idx]);

    for(i = 0; i < 10; i = i + 1) begin
        inputs = 040190218 + i + 5;
        cin = inputs;
        for(j = 0; j < 4; j = j + 1) begin
            inputs = 040190218+ i + j;
            $display("inputs = %d, %b", inputs, inputs);
            x[j] = inputs;
        end
        #10;
    end
    
    cin = 32'hFFFFFFFF;
    x[0] = 32'hFFFFFFFF;
    x[1] = 32'hFFFFFFFF;
    x[2] = 32'hFFFFFFFF;
    x[3] = 32'hFFFFFFFF;
    #10;

$finish;
end

endmodule

waveforms/Compressor_42.vcd
$date
	Sat Apr  1 17:00:57 2023
$end
$version
	Icarus Verilog
$end
$timescale
	1s
$end
$scope module Compressor_42_tb $end
$var wire 32 ! s [31:0] $end
$var wire 32 " cout [31:0] $end
$var wire 32 # c [31:0] $end
$var reg 32 $ cin [31:0] $end
$var reg 32 % inputs [31:0] $end
$var integer 32 & i [31:0] $end
$var integer 32 ' idx [31:0] $end
$var integer 32 ( j [31:0] $end
$scope module compressor_42 $end
$var wire 32 ) cin [31:0] $end
$var wire 32 * sum_fa1 [31:0] $end
$var wire 32 + s [31:0] $end
$var wire 32 , cout [31:0] $end
$var wire 32 - c [31:0] $end
$scope module fa1 $end
$var wire 32 . A [31:0] $end
$var wire 32 / B [31:0] $end
$var wire 32 0 Cin [31:0] $end
$var wire 32 1 S [31:0] $end
$var wire 32 2 Cout [31:0] $end
$upscope $end
$scope module fa2 $end
$var wire 32 3 A [31:0] $end
$var wire 32 4 B [31:0] $end
$var wire 32 5 Cin [31:0] $end
$var wire 32 6 S [31:0] $end
$var wire 32 7 Cout [31:0] $end
$upscope $end
$upscope $end
$upscope $end
$scope module Compressor_42_tb $end
$var reg 32 8 \x[0] [31:0] $end
$upscope $end
$scope module Compressor_42_tb $end
$var reg 32 9 \x[1] [31:0] $end
$upscope $end
$scope module Compressor_42_tb $end
$var reg 32 : \x[2] [31:0] $end
$upscope $end
$scope module Compressor_42_tb $end
$var reg 32 ; \x[3] [31:0] $end
$upscope $end
$enddefinitions $end
$comment Show the parameter values. $end
$dumpall
$end
#0
$dumpvars
b10011001010100000100001101 ;
b10011001010100000100001100 :
b10011001010100000100001011 9
b10011001010100000100001010 8
b0 7
b1011111110100100010100111101 6
b10011001010100000100001111 5
b111001011111100001100100001 4
b10011001010100000100001101 3
b0 2
b111001011111100001100100001 1
b10011001010100000100001100 0
b10011001010100000100001011 /
b10011001010100000100001010 .
b0 -
b0 ,
b1011111110100100010100111101 +
b111001011111100001100100001 *
b10011001010100000100001111 )
b100 (
b100 '
b0 &
b10011001010100000100001101 %
b10011001010100000100001111 $
b0 #
b0 "
b1011111110100100010100111101 !
$end
#10
b111001011111100001100100100 *
b111001011111100001100100100 1
b111001011111100001100100100 4
b1011111110100100010101000010 !
b1011111110100100010101000010 +
b1011111110100100010101000010 6
b10011001010100000100001110 ;
b10011001010100000100001110 3
b10011001010100000100001101 :
b10011001010100000100001101 0
b10011001010100000100001100 9
b10011001010100000100001100 /
b10011001010100000100001011 8
b10011001010100000100001011 .
b100 (
b10011001010100000100010000 $
b10011001010100000100010000 )
b10011001010100000100010000 5
b10011001010100000100001110 %
b1 &
#20
b111001011111100001100100111 *
b111001011111100001100100111 1
b111001011111100001100100111 4
b1011111110100100010101000111 !
b1011111110100100010101000111 +
b1011111110100100010101000111 6
b10011001010100000100001111 ;
b10011001010100000100001111 3
b10011001010100000100001110 :
b10011001010100000100001110 0
b10011001010100000100001101 9
b10011001010100000100001101 /
b10011001010100000100001100 8
b10011001010100000100001100 .
b100 (
b10011001010100000100010001 $
b10011001010100000100010001 )
b10011001010100000100010001 5
b10011001010100000100001111 %
b10 &
#30
b111001011111100001100101010 *
b111001011111100001100101010 1
b111001011111100001100101010 4
b1011111110100100010101001100 !
b1011111110100100010101001100 +
b1011111110100100010101001100 6
b10011001010100000100010000 ;
b10011001010100000100010000 3
b10011001010100000100001111 :
b10011001010100000100001111 0
b10011001010100000100001110 9
b10011001010100000100001110 /
b10011001010100000100001101 8
b10011001010100000100001101 .
b100 (
b10011001010100000100010010 $
b10011001010100000100010010 )
b10011001010100000100010010 5
b10011001010100000100010000 %
b11 &
#40
b111001011111100001100101101 *
b111001011111100001100101101 1
b111001011111100001100101101 4
b1011111110100100010101010001 !
b1011111110100100010101010001 +
b1011111110100100010101010001 6
b10011001010100000100010001 ;
b10011001010100000100010001 3
b10011001010100000100010000 :
b10011001010100000100010000 0
b10011001010100000100001111 9
b10011001010100000100001111 /
b10011001010100000100001110 8
b10011001010100000100001110 .
b100 (
b10011001010100000100010011 $
b10011001010100000100010011 )
b10011001010100000100010011 5
b10011001010100000100010001 %
b100 &
#50
b111001011111100001100110000 *
b111001011111100001100110000 1
b111001011111100001100110000 4
b1011111110100100010101010110 !
b1011111110100100010101010110 +
b1011111110100100010101010110 6
b10011001010100000100010010 ;
b10011001010100000100010010 3
b10011001010100000100010001 :
b10011001010100000100010001 0
b10011001010100000100010000 9
b10011001010100000100010000 /
b10011001010100000100001111 8
b10011001010100000100001111 .
b100 (
b10011001010100000100010100 $
b10011001010100000100010100 )
b10011001010100000100010100 5
b10011001010100000100010010 %
b101 &
#60
b111001011111100001100110011 *
b111001011111100001100110011 1
b111001011111100001100110011 4
b1011111110100100010101011011 !
b1011111110100100010101011011 +
b1011111110100100010101011011 6
b10011001010100000100010011 ;
b10011001010100000100010011 3
b10011001010100000100010010 :
b10011001010100000100010010 0
b10011001010100000100010001 9
b10011001010100000100010001 /
b10011001010100000100010000 8
b10011001010100000100010000 .
b100 (
b10011001010100000100010101 $
b10011001010100000100010101 )
b10011001010100000100010101 5
b10011001010100000100010011 %
b110 &
#70
b111001011111100001100110110 *
b111001011111100001100110110 1
b111001011111100001100110110 4
b1011111110100100010101100000 !
b1011111110100100010101100000 +
b1011111110100100010101100000 6
b10011001010100000100010100 ;
b10011001010100000100010100 3
b10011001010100000100010011 :
b10011001010100000100010011 0
b10011001010100000100010010 9
b10011001010100000100010010 /
b10011001010100000100010001 8
b10011001010100000100010001 .
b100 (
b10011001010100000100010110 $
b10011001010100000100010110 )
b10011001010100000100010110 5
b10011001010100000100010100 %
b111 &
#80
b111001011111100001100111001 *
b111001011111100001100111001 1
b111001011111100001100111001 4
b1011111110100100010101100101 !
b1011111110100100010101100101 +
b1011111110100100010101100101 6
b10011001010100000100010101 ;
b10011001010100000100010101 3
b10011001010100000100010100 :
b10011001010100000100010100 0
b10011001010100000100010011 9
b10011001010100000100010011 /
b10011001010100000100010010 8
b10011001010100000100010010 .
b100 (
b10011001010100000100010111 $
b10011001010100000100010111 )
b10011001010100000100010111 5
b10011001010100000100010101 %
b1000 &
#90
b111001011111100001100111100 *
b111001011111100001100111100 1
b111001011111100001100111100 4
b1011111110100100010101101010 !
b1011111110100100010101101010 +
b1011111110100100010101101010 6
b10011001010100000100010110 ;
b10011001010100000100010110 3
b10011001010100000100010101 :
b10011001010100000100010101 0
b10011001010100000100010100 9
b10011001010100000100010100 /
b10011001010100000100010011 8
b10011001010100000100010011 .
b100 (
b10011001010100000100011000 $
b10011001010100000100011000 )
b10011001010100000100011000 5
b10011001010100000100010110 %
b1001 &
#100
b11111111111111111111111111111101 *
b11111111111111111111111111111101 1
b11111111111111111111111111111101 4
b10 "
b10 ,
b10 2
b11111111111111111111111111111011 !
b11111111111111111111111111111011 +
b11111111111111111111111111111011 6
b10 #
b10 -
b10 7
b11111111111111111111111111111111 ;
b11111111111111111111111111111111 3
b11111111111111111111111111111111 :
b11111111111111111111111111111111 0
b11111111111111111111111111111111 9
b11111111111111111111111111111111 /
b11111111111111111111111111111111 8
b11111111111111111111111111111111 .
b11111111111111111111111111111111 $
b11111111111111111111111111111111 )
b11111111111111111111111111111111 5
b1010 &
